geoidlab/__init__.py
geoidlab/__version__.py
geoidlab/constants.py
geoidlab/coordinates.py
geoidlab/dem.py
geoidlab/dem_old.py
geoidlab/dtm.py
geoidlab/geoid.py
geoidlab/geoid1.py
geoidlab/geoid_old.py
geoidlab/ggm.py
geoidlab/gravity.py
geoidlab/icgem.py
geoidlab/legendre.py
geoidlab/legendre1.py
geoidlab/plot.py
geoidlab/shtools.py
geoidlab/stokes_func.py
geoidlab/stokes_func1.py
geoidlab/terrain.py
geoidlab/tide.py
geoidlab/cli/__init__.py
geoidlab/cli/main.py
geoidlab/cli/commands/__init__.py
geoidlab/cli/commands/geoid.py
geoidlab/cli/commands/helmert.py
geoidlab/cli/commands/info.py
geoidlab/cli/commands/plot.py
geoidlab/cli/commands/reference.py
geoidlab/cli/commands/topo.py
geoidlab/cli/commands/utils/common.py
geoidlab/cli/old/geoidApp.py
geoidlab/cli/old/commands/__init__.py
geoidlab/cli/old/commands/compute.py
geoidlab/cli/old/commands/download.py
geoidlab/cli/old/commands/geoid.py
geoidlab/cli/old/commands/grid.py
geoidlab/cli/old/commands/init.py
geoidlab/cli/old/commands/process.py
geoidlab/cli/old/commands/validate.py
geoidlab/cli/old/commands/visualize.py
geoidlab/cli/utils/__init__.py
geoidlab/cli/utils/config_parser.py
geoidlab/data/DTM2006.xz
geoidlab/data/README.V11.txt
geoidlab/mapping/__init__.py
geoidlab/mapping/colormaps.py
geoidlab/mapping/get_cpt.py
geoidlab/mapping/cpt/BlWhRe.cpt
geoidlab/mapping/cpt/BlueDarkRed18.cpt
geoidlab/mapping/cpt/BlueWhiteOrangeRed.cpt
geoidlab/mapping/cpt/BlueYellowRed.cpt
geoidlab/mapping/cpt/Blues_09.cpt
geoidlab/mapping/cpt/Caribbean.cpt
geoidlab/mapping/cpt/DEM_poster.cpt
geoidlab/mapping/cpt/DEM_print.cpt
geoidlab/mapping/cpt/DEM_screen.cpt
geoidlab/mapping/cpt/ETOPO1-Reed.cpt
geoidlab/mapping/cpt/ETOPO1.cpt
geoidlab/mapping/cpt/GMT_dem1.cpt
geoidlab/mapping/cpt/GMT_globe.cpt
geoidlab/mapping/cpt/GMT_gray.cpt
geoidlab/mapping/cpt/GMT_haxby.cpt
geoidlab/mapping/cpt/GMT_hot.cpt
geoidlab/mapping/cpt/GMT_no_green.cpt
geoidlab/mapping/cpt/GMT_ocean.cpt
geoidlab/mapping/cpt/GMT_panoply.cpt
geoidlab-1.0.6.dist-info/licenses/LICENSE
geoidlab-1.0.6.dist-info/METADATA
geoidlab-1.0.6.dist-info/WHEEL
geoidlab-1.0.6.dist-info/entry_points.txt
geoidlab-1.0.6.dist-info/top_level.txt
geoidlab-1.0.6.dist-info/RECORD
