Metadata-Version: 2.4
Name: geoidlab
Version: 1.0.6
Summary: GeoidLab: A Modular and Automated Python Package for Geoid Computation
Home-page: https://github.com/cikelly/geoidlab
Author: Caleb Kelly
Author-email: Caleb Kelly <geo.calebkelly@gmail.com>
License-Expression: GPL-3.0-or-later
Project-URL: Homepage, https://github.com/cikelly/geoidlab
Project-URL: Documentation, https://geoidlab.readthedocs.io
Project-URL: Repository, https://github.com/cikelly/geoidlab
Project-URL: Changelog, https://github.com/cikelly/geoidlab/blob/main/CHANGELOG.md
Project-URL: Issues, https://github.com/cikelly/geoidlab/issues
Classifier: Development Status :: 4 - Beta
Classifier: Intended Audience :: Science/Research
Classifier: Programming Language :: Python :: 3
Classifier: Programming Language :: Python :: 3.8
Classifier: Programming Language :: Python :: 3.9
Classifier: Programming Language :: Python :: 3.10
Classifier: Programming Language :: Python :: 3.11
Classifier: Programming Language :: Python :: 3.12
Classifier: Topic :: Scientific/Engineering :: GIS
Classifier: Topic :: Scientific/Engineering :: Physics
Requires-Python: >=3.8,<3.13
License-File: LICENSE
Requires-Dist: numpy<2.0.0,>=1.20.0
Requires-Dist: scipy<2.0.0,>=1.7.0
Requires-Dist: requests>=2.25.0
Requires-Dist: tqdm>=4.60.0
Requires-Dist: beautifulsoup4>=4.9.0
Requires-Dist: xarray>=0.19.0
Requires-Dist: netCDF4>=1.5.7
Requires-Dist: pandas<3.0.0,>=1.3.0
Requires-Dist: numba>=0.53.0
Requires-Dist: numba-progress>=0.0.3
Requires-Dist: openpyxl>=3.0.7
Requires-Dist: rasterio>=1.2.0
Requires-Dist: rioxarray>=0.5.0
Requires-Dist: bottleneck>=1.3.2
Requires-Dist: scikit-learn<2.0.0,>=0.24.0
Requires-Dist: joblib>=1.3.0
Requires-Dist: matplotlib<4.0.0,>=3.4.0
Requires-Dist: pyproj<4.0.0,>=3.0.0
Requires-Dist: packaging>=21.0
Requires-Dist: ipython>=8.0.0
Provides-Extra: dev
Requires-Dist: pytest>=6.0; extra == "dev"
Requires-Dist: pytest-cov>=2.0; extra == "dev"
Requires-Dist: black>=21.0; extra == "dev"
Requires-Dist: flake8>=3.9; extra == "dev"
Requires-Dist: mypy>=0.900; extra == "dev"
Requires-Dist: sphinx>=4.0; extra == "dev"
Requires-Dist: sphinx-rtd-theme>=1.0; extra == "dev"
Requires-Dist: twine>=3.4; extra == "dev"
Requires-Dist: build>=0.7; extra == "dev"
Dynamic: author
Dynamic: home-page
Dynamic: license-file
Dynamic: requires-python
